check_breach_password/__init__.py
check_breach_password/check_breach.py
check_breach_password/cli/__init__.py
check_breach_password/cli/cli.py
check_breach_password/cli/commands/__init__.py
check_breach_password/cli/commands/check.py
password_breach_CLI-1.1.dist-info/METADATA
password_breach_CLI-1.1.dist-info/WHEEL
password_breach_CLI-1.1.dist-info/entry_points.txt
password_breach_CLI-1.1.dist-info/top_level.txt
password_breach_CLI-1.1.dist-info/RECORD
