Metadata-Version: 2.1
Name: password-breach-CLI
Version: 1.1
Summary: Check if a password has been breached in all registered data leaks
Home-page: UNKNOWN
Author: Sanjeev Bhusal
Author-email: bhusalsanjeev23@gmail.com
License: UNKNOWN
Keywords: python,click,password-breach,pwnedpasswords
Platform: UNKNOWN
Requires-Dist: click
